{
    "chapters": [
        {
            "title": "Digital Investment: An Overview",
            "summary": "This chapter provides a comprehensive introduction to digital investment, including its definition and the benefits it offers.",
            "keywords": [
                "digital investment",
                "definition",
                "benefits"
            ]
        },
        {
            "title": "Understanding Digital Investment",
            "summary": "Explore the concept of digital investment and how it differs from traditional investment methods. Learn about the key elements that define digital investment.",
            "keywords": [
                "digital investment",
                "definition"
            ]
        },
        {
            "title": "Benefits of Digital Investment",
            "summary": "Discover the numerous advantages of digital investment, including increased accessibility, lower costs, and enhanced diversification opportunities.",
            "keywords": [
                "digital investment",
                "benefits"
            ]
        },
        {
            "title": "The Future of Digital Investment",
            "summary": "Look into the future of digital investment and how it is shaping the financial landscape. Understand the potential for growth and innovation in this sector.",
            "keywords": [
                "digital investment",
                "future",
                "innovation"
            ]
        }
    ]
}