{
    "chapters": [
        {
            "title": "Transparency in Blockchain",
            "summary": "This chapter delves into the concept of transparency in blockchain technology. It explains how the decentralized nature of blockchain ensures that all participants have access to the same information, promoting openness and accountability.",
            "keywords": [
                "transparency",
                "decentralization",
                "openness",
                "accountability"
            ]
        },
        {
            "title": "Building Trust with Blockchain",
            "summary": "This chapter explores how blockchain builds trust among participants. It discusses the role of immutability, consensus mechanisms, and cryptographic security in establishing a trustworthy environment.",
            "keywords": [
                "trust",
                "immutability",
                "consensus",
                "cryptographic security"
            ]
        },
        {
            "title": "Applications of Blockchain Technology",
            "summary": "This chapter covers various applications of blockchain technology across different industries. It highlights use cases in finance, supply chain management, healthcare, and more, demonstrating the versatility of blockchain.",
            "keywords": [
                "applications",
                "finance",
                "supply chain",
                "healthcare"
            ]
        },
        {
            "title": "Understanding Blockchain Fundamentals",
            "summary": "This chapter provides an overview of the fundamental concepts of blockchain technology. It explains the structure of a blockchain, the role of nodes, and the process of adding new blocks to the chain.",
            "keywords": [
                "blockchain",
                "nodes",
                "blocks",
                "fundamentals"
            ]
        }
    ]
}